{
  "$schema": "https://ui.shadcn.com/schema/registry-item.json",
  "name": "RequiredPick",
  "type": "registry:lib",
  "title": "RequiredPick",
  "description": "by default, the required makes everything required, but you can use this type to make a required pick of a type.",
  "files": [
    {
      "path": "src/registry/types/RequiredPick/RequiredPick.ts",
      "content": "export type RequiredPick<T, Key extends keyof T> = Required<Pick<T, Key>> & T;\n",
      "type": "registry:lib",
      "target": "src/types/RequiredPick.ts"
    }
  ],
  "meta": {
    "url": "/snippets/types/RequiredPick"
  }
}